setup.py
acl_plugin/__init__.py
acl_plugin/acl_plugin.py
bottle_aclPlugin.egg-info/PKG-INFO
bottle_aclPlugin.egg-info/SOURCES.txt
bottle_aclPlugin.egg-info/dependency_links.txt
bottle_aclPlugin.egg-info/top_level.txt